{
    "apps": {
        // "B6sIXKLiin": {
        //     "siteId": [
        //         "627683"
        //     ],
        //     "atiUrl": "https://piano-ingest-composer.ati-host.net",
        //     "exchangeRate": {},
        //     "disablePageDisplay": false
        // },
        // "mbs77qtzUz": {
        //     "siteId": [
        //         "630372"
        //     ],
        //     "atiUrl": "https://piano-ingest-composer.ati-host.net",
        //     "exchangeRate": {},
        //     "disablePageDisplay": false
        // },
        // "qlu5NxAypu": {
        //     "siteId": [
        //         "631533"
        //     ],
        //     "atiUrl": "https://piano-ingest-composer.ati-host.net",
        //     "exchangeRate": {},
        //     "disablePageDisplay": false
        // },
        // "DC3REpZYpu": {
        //     "siteId": [
        //         "631407"
        //     ],
        //     "atiUrl": "https://piano-ingest-composer.ati-host.net",
        //     "exchangeRate": {},
        //     "disablePageDisplay": false
        // },
        // "lQE8zvEWpu": {
        //     "siteId": [
        //         "631663"
        //     ],
        //     "atiUrl": "https://piano-ingest-composer.ati-host.net",
        //     "exchangeRate": {},
        //     "disablePageDisplay": false
        // },
        // "7JJs2o4rpu": {
        //     "siteId": [
        //         "631659"
        //     ],
        //     "atiUrl": "https://piano-ingest-composer.ati-host.net",
        //     "exchangeRate": {},
        //     "disablePageDisplay": false
        // },
        // "SFO7B4zlpu": {
        //     "siteId": [
        //         "631662"
        //     ],
        //     "atiUrl": "https://piano-ingest-composer.ati-host.net",
        //     "exchangeRate": {},
        //     "disablePageDisplay": false
        // },
        // "uGuUWn5zpu": {
        //     "siteId": [
        //         "631664"
        //     ],
        //     "atiUrl": "https://piano-ingest-composer.ati-host.net",
        //     "exchangeRate": {},
        //     "disablePageDisplay": false
        // },
        // "zUShAI0Opu": {
        //     "siteId": [
        //         "632874"
        //     ],
        //     "atiUrl": "https://piano-ingest-composer.ati-host.net",
        //     "exchangeRate": {},
        //     "disablePageDisplay": false
        // },
        // "0GyWVelQpu": {
        //     "siteId": [
        //         "637114"
        //     ],
        //     "atiUrl": "https://piano-ingest-composer.ati-host.net",
        //     "exchangeRate": {},
        //     "disablePageDisplay": false
        // },
        // "3UHressLnd": {
        //     "siteId": [
        //         "631685"
        //     ],
        //     "atiUrl": "https://piano-ingest-composer.ati-host.net",
        //     "exchangeRate": {},
        //     "disablePageDisplay": false
        // },
        // "m5PazUWdpu": {
        //     "siteId": [
        //         "632045"
        //     ],
        //     "atiUrl": "https://piano-ingest-composer.ati-host.net",
        //     "exchangeRate": {},
        //     "disablePageDisplay": false
        // },
        // "UFwY8fonpu": {
        //     "siteId": [
        //         "632049"
        //     ],
        //     "atiUrl": "https://piano-ingest-composer.ati-host.net",
        //     "exchangeRate": {},
        //     "disablePageDisplay": false
        // },
        // "SwhouE5cpu": {
        //     "siteId": [
        //         "632050"
        //     ],
        //     "atiUrl": "https://piano-ingest-composer.ati-host.net",
        //     "exchangeRate": {},
        //     "disablePageDisplay": false
        // },
        // "F3JePD8ppu": {
        //     "siteId": [
        //         "632051"
        //     ],
        //     "atiUrl": "https://piano-ingest-composer.ati-host.net",
        //     "exchangeRate": {},
        //     "disablePageDisplay": false
        // },
        // "CDq5SCnBpu": {
        //     "siteId": [
        //         "632048"
        //     ],
        //     "atiUrl": "https://piano-ingest-composer.ati-host.net",
        //     "exchangeRate": {},
        //     "disablePageDisplay": false
        // },
        // "B6Jiz8CIpu": {
        //     "siteId": [
        //         "632047"
        //     ],
        //     "atiUrl": "https://piano-ingest-composer.ati-host.net",
        //     "exchangeRate": {},
        //     "disablePageDisplay": false
        // },
        // "5SmJcLoipu": {
        //     "siteId": [
        //         "632052"
        //     ],
        //     "atiUrl": "https://piano-ingest-composer.ati-host.net",
        //     "exchangeRate": {},
        //     "disablePageDisplay": false
        // },
        // "LOUPhyaVpu": {
        //     "siteId": [
        //         "632054"
        //     ],
        //     "atiUrl": "https://piano-ingest-composer.ati-host.net",
        //     "exchangeRate": {},
        //     "disablePageDisplay": false
        // },
        // "zeDzY7lApu": {
        //     "siteId": [
        //         "632056"
        //     ],
        //     "atiUrl": "https://piano-ingest-composer.ati-host.net",
        //     "exchangeRate": {},
        //     "disablePageDisplay": false
        // },
        // "KLoewj2Gpu": {
        //     "siteId": [
        //         "632055"
        //     ],
        //     "atiUrl": "https://piano-ingest-composer.ati-host.net",
        //     "exchangeRate": {},
        //     "disablePageDisplay": false
        // },
        // "SQqkfckupu": {
        //     "siteId": [
        //         "632053"
        //     ],
        //     "atiUrl": "https://piano-ingest-composer.ati-host.net",
        //     "exchangeRate": {},
        //     "disablePageDisplay": false
        // },
        // "Sqhs7z60pu": {
        //     "siteId": [
        //         "632057"
        //     ],
        //     "atiUrl": "https://piano-ingest-composer.ati-host.net",
        //     "exchangeRate": {},
        //     "disablePageDisplay": false
        // },
        // "9ENxKQ58pu": {
        //     "siteId": [
        //         "632505"
        //     ],
        //     "atiUrl": "https://piano-ingest-composer.ati-host.net",
        //     "exchangeRate": {},
        //     "disablePageDisplay": false
        // },
        // "L6MBXcalpu": {
        //     "siteId": [
        //         "632738"
        //     ],
        //     "atiUrl": "https://piano-ingest-composer.ati-host.net",
        //     "exchangeRate": {},
        //     "disablePageDisplay": false
        // },
        // "dXh0df61pu": {
        //     "siteId": [
        //         "632739"
        //     ],
        //     "atiUrl": "https://piano-ingest-composer.ati-host.net",
        //     "exchangeRate": {},
        //     "disablePageDisplay": false
        // },
        // "rY0WWCfrpu": {
        //     "siteId": [
        //         "632740"
        //     ],
        //     "atiUrl": "https://piano-ingest-composer.ati-host.net",
        //     "exchangeRate": {},
        //     "disablePageDisplay": false
        // },
        // "jZDJSQc4pu": {
        //     "siteId": [
        //         "632741"
        //     ],
        //     "atiUrl": "https://piano-ingest-composer.ati-host.net",
        //     "exchangeRate": {},
        //     "disablePageDisplay": false
        // },
        // "qv5x5utGpu": {
        //     "siteId": [
        //         "632737"
        //     ],
        //     "atiUrl": "https://piano-ingest-composer.ati-host.net",
        //     "exchangeRate": {},
        //     "disablePageDisplay": false
        // },
        // "OKoak6s4pu": {
        //     "siteId": [
        //         "633009"
        //     ],
        //     "atiUrl": "https://piano-ingest-composer.ati-host.net",
        //     "exchangeRate": {},
        //     "disablePageDisplay": false
        // },
        // "Yg8MRycIpu": {
        //     "siteId": [
        //         "633010"
        //     ],
        //     "atiUrl": "https://piano-ingest-composer.ati-host.net",
        //     "exchangeRate": {},
        //     "disablePageDisplay": false
        // },
        // "p7sVIGTDn5": {
        //     "siteId": [
        //         "634871"
        //     ],
        //     "atiUrl": "https://piano-ingest-composer.ati-host.net",
        //     "exchangeRate": {},
        //     "disablePageDisplay": false
        // },
        // "7bDTlJZTpu": {
        //     "siteId": [
        //         "634853"
        //     ],
        //     "atiUrl": "https://piano-ingest-composer.ati-host.net",
        //     "exchangeRate": {},
        //     "disablePageDisplay": false
        // },
        // "hph4LAYuC6": {
        //     "siteId": [
        //         "635851",
                "639545"
        //     ],
        //     "atiUrl": "https://piano-ingest-composer.ati-host.net",
        //     "exchangeRate": {},
        //     "disablePageDisplay": false
        // },
        // "beVmoi3WRm": {
        //     "siteId": [
        //         "636023"
        //     ],
        //     "atiUrl": "https://piano-ingest-composer.ati-host.net",
        //     "exchangeRate": {},
        //     "disablePageDisplay": false
        // },
        // "c62mMqyQpu": {
        //     "siteId": [
        //         "636067"
        //     ],
        //     "atiUrl": "https://piano-ingest-composer.ati-host.net",
        //     "exchangeRate": {},
        //     "disablePageDisplay": false
        // },
        // "cfQj2fM3zj": {
        //     "siteId": [
        //         "636407"
        //     ],
        //     "atiUrl": "https://piano-ingest-composer.ati-host.net",
        //     "exchangeRate": {},
        //     "disablePageDisplay": false
        // },
        // "TaNnjtWYpu": {
        //     "siteId": [
        //         "636422"
        //     ],
        //     "atiUrl": "https://piano-ingest-composer.ati-host.net",
        //     "exchangeRate": {
        //         "USD": 3.673
        //     },
        //     "disablePageDisplay": false
        // },
        // "Xi7fMnt7pu": {
        //     "siteId": [
        //         "636855"
        //     ],
        //     "atiUrl": "https://piano-ingest-composer.ati-host.net",
        //     "exchangeRate": {},
        //     "disablePageDisplay": false
        // },
        // "28WtJlio6C": {
        //     "siteId": [
        //         "636639"
        //     ],
        //     "atiUrl": "https://piano-ingest-composer.ati-host.net",
        //     "exchangeRate": {},
        //     "disablePageDisplay": false
        // },
        // "P3Z2gSespu": {
        //     "siteId": [
        //         "640146"
        //     ],
        //     "atiUrl": "https://piano-ingest-composer.ati-host.net",
        //     "exchangeRate": {},
        //     "disablePageDisplay": false
        // },
        // "gL0Np9Mqpu": {
        //     "siteId": [
        //         "640996"
        //     ],
        //     "atiUrl": "https://piano-ingest-composer.ati-host.net",
        //     "exchangeRate": {},
        //     "disablePageDisplay": false
        // },
        // "wQKkKmsRpu": {
        //     "siteId": [
        //         "641868"
        //     ],
        //     "atiUrl": "https://piano-ingest-composer.ati-host.net",
        //     "exchangeRate": {},
        //     "disablePageDisplay": false
        // },
        // "PFwDcEgKpu": {
        //     "siteId": [
        //         "641869"
        //     ],
        //     "atiUrl": "https://piano-ingest-composer.ati-host.net",
        //     "exchangeRate": {},
        //     "disablePageDisplay": false
        // },
        // "1BZxNTtRpu": {
        //     "siteId": [
        //         "642196"
        //     ],
        //     "atiUrl": "https://piano-ingest-composer.ati-host.net",
        //     "exchangeRate": {},
        //     "disablePageDisplay": false
        // },
        // "77U9mvKhpu": {
        //     "siteId": [
        //         "635177"
        //     ],
        //     "atiUrl": "https://piano-ingest-composer.ati-host.net",
        //     "exchangeRate": {},
        //     "disablePageDisplay": false
        // },
        // "aG4QZwTKpu": {
        //     "siteId": [
        //         "642464"
        //     ],
        //     "atiUrl": "https://piano-ingest-composer.ati-host.net",
        //     "exchangeRate": {},
        //     "disablePageDisplay": false
        // },
        // "QlkmWaltpu": {
        //     "siteId": [
        //         "642485"
        //     ],
        //     "atiUrl": "https://piano-ingest-composer.ati-host.net",
        //     "exchangeRate": {},
        //     "disablePageDisplay": false
        // },
        // "xZyCF7VIpu": {
        //     "siteId": [
        //         "632599"
        //     ],
        //     "atiUrl": "https://piano-ingest-composer.ati-host.net",
        //     "exchangeRate": {},
        //     "disablePageDisplay": false
        // },
        // "6PG328gepu": {
        //     "siteId": [
        //         "642332"
        //     ],
        //     "atiUrl": "https://piano-ingest-composer.ati-host.net",
        //     "exchangeRate": {},
        //     "disablePageDisplay": true
        // },
        // "Jo36t1Kwpu": {
        //     "siteId": [
        //         "642813"
        //     ],
        //     "atiUrl": "https://piano-ingest-composer.ati-host.net",
        //     "exchangeRate": {},
        //     "disablePageDisplay": false
        // },
    //     "dEekW8d5l8": {
    //         "siteId": [
    //             "642983"
    //         ],
    //         "atiUrl": "https://piano-ingest-composer-sandbox.ati-host.net",
    //         "exchangeRate": {},
    //         "disablePageDisplay": false
    //     }
    // }
}